llama_index/readers/singlestore/__init__.py
llama_index/readers/singlestore/base.py
llama_index_readers_singlestore-0.4.0.dist-info/METADATA
llama_index_readers_singlestore-0.4.0.dist-info/WHEEL
llama_index_readers_singlestore-0.4.0.dist-info/licenses/LICENSE
llama_index_readers_singlestore-0.4.0.dist-info/RECORD
