Metadata-Version: 2.4
Name: llama-index-readers-singlestore
Version: 0.4.0
Summary: llama-index readers singlestore integration
Author-email: Your Name <you@example.com>
Maintainer: singlestore
License-Expression: MIT
License-File: LICENSE
Keywords: memsql,singlestore
Requires-Python: <4.0,>=3.9
Requires-Dist: llama-index-core<0.14,>=0.13.0
Requires-Dist: llama-index-readers-database<0.6,>=0.5.0
Requires-Dist: pymysql<2,>=1.1.0
